{
    "adult": false,
    "backdrop_path": "/qJcUobr34c77YRQQ7zacTNrBdKj.jpg",
    "belongs_to_collection": null,
    "budget": 5000000,
    "genres": [
        {
            "id": 12,
            "name": "Adventure"
        },
        {
            "id": 27,
            "name": "Horror"
        }
    ],
    "homepage": "",
    "id": 171424,
    "imdb_id": "tt2403021",
    "origin_country": [
        "CA",
        "US"
    ],
    "original_language": "en",
    "original_title": "The Green Inferno",
    "overview": "A group of student activists travel from New York City to the Amazon to save the rainforest.  However, once they arrive in this vast green landscape, they soon discover that they are not alone\u2026 and that no good deed goes unpunished.",
    "popularity": 3.1464,
    "poster_path": "/dTnAYyUwp6lT0cKrt4aNujj5mdF.jpg",
    "production_companies": [
        {
            "id": 55497,
            "logo_path": null,
            "name": "Sobras International Pictures",
            "origin_country": "CL"
        },
        {
            "id": 9015,
            "logo_path": "/pRQLCm8AAPXL7H9MzX4xuS8GGg8.png",
            "name": "Worldview Entertainment",
            "origin_country": "US"
        },
        {
            "id": 18142,
            "logo_path": null,
            "name": "Dragonfly Entertainment",
            "origin_country": "US"
        },
        {
            "id": 73625,
            "logo_path": "/7EXbyLJBKifYXWZgOjR5M3qhyei.png",
            "name": "BH Tilt",
            "origin_country": "US"
        }
    ],
    "production_countries": [
        {
            "iso_3166_1": "CA",
            "name": "Canada"
        },
        {
            "iso_3166_1": "CL",
            "name": "Chile"
        },
        {
            "iso_3166_1": "US",
            "name": "United States of America"
        }
    ],
    "release_date": "2013-09-08",
    "revenue": 12931420,
    "runtime": 100,
    "spoken_languages": [
        {
            "english_name": "English",
            "iso_639_1": "en",
            "name": "English"
        }
    ],
    "status": "Released",
    "tagline": "Fear will eat you alive.",
    "title": "The Green Inferno",
    "video": false,
    "vote_average": 5.74,
    "vote_count": 1550,
    "youtube_theme_added": 1719854634,
    "youtube_theme_added_by": "118304977",
    "youtube_theme_edited": 1719854634,
    "youtube_theme_edited_by": "118304977",
    "youtube_theme_url": "https://www.youtube.com/watch?v=Ns0J50nk61k"
}