{
    "adult": false,
    "backdrop_path": "/pHFNaNHqiaZ2myMAsylIm2y17c7.jpg",
    "belongs_to_collection": null,
    "budget": 14000000,
    "genres": [
        {
            "id": 18,
            "name": "Drama"
        },
        {
            "id": 10752,
            "name": "War"
        },
        {
            "id": 53,
            "name": "Thriller"
        },
        {
            "id": 36,
            "name": "History"
        }
    ],
    "homepage": "http://www.ifcfilms.com/films/the-catcher-was-a-spy",
    "id": 467952,
    "imdb_id": "tt4602066",
    "origin_country": [
        "US"
    ],
    "original_language": "en",
    "original_title": "The Catcher Was a Spy",
    "overview": "Former major league baseball player Moe Berg lives a double life working for the Office of Strategic Services in World War II Europe.",
    "popularity": 1.3031,
    "poster_path": "/3aBv9Oln0aoBrEbkMabHIVat6CY.jpg",
    "production_companies": [
        {
            "id": 64541,
            "logo_path": null,
            "name": "Serena Films",
            "origin_country": ""
        },
        {
            "id": 4135,
            "logo_path": "/8lz5brU6aEkKBnawP5NOU1fvhCP.png",
            "name": "Animus Films",
            "origin_country": "US"
        },
        {
            "id": 24277,
            "logo_path": "/mRSBVNNL2lZvJKVGjlxeUQVRc6X.png",
            "name": "PalmStar Media",
            "origin_country": "US"
        },
        {
            "id": 42582,
            "logo_path": null,
            "name": "Finch Entertainment",
            "origin_country": "US"
        },
        {
            "id": 18922,
            "logo_path": "/yPIwZuQRnUlHMzuwluiOVMrUxn4.png",
            "name": "Windy Hill Pictures",
            "origin_country": "US"
        }
    ],
    "production_countries": [
        {
            "iso_3166_1": "US",
            "name": "United States of America"
        }
    ],
    "release_date": "2018-06-22",
    "revenue": 953953,
    "runtime": 94,
    "spoken_languages": [
        {
            "english_name": "English",
            "iso_639_1": "en",
            "name": "English"
        },
        {
            "english_name": "French",
            "iso_639_1": "fr",
            "name": "Fran\u00e7ais"
        },
        {
            "english_name": "German",
            "iso_639_1": "de",
            "name": "Deutsch"
        },
        {
            "english_name": "Hebrew",
            "iso_639_1": "he",
            "name": "\u05e2\u05b4\u05d1\u05b0\u05e8\u05b4\u05d9\u05ea"
        },
        {
            "english_name": "Italian",
            "iso_639_1": "it",
            "name": "Italiano"
        },
        {
            "english_name": "Japanese",
            "iso_639_1": "ja",
            "name": "\u65e5\u672c\u8a9e"
        }
    ],
    "status": "Released",
    "tagline": "Based on the true story of Moe Berg",
    "title": "The Catcher Was a Spy",
    "video": false,
    "vote_average": 6.202,
    "vote_count": 310,
    "youtube_theme_added": 1717510064,
    "youtube_theme_added_by": "118304977",
    "youtube_theme_edited": 1717510064,
    "youtube_theme_edited_by": "118304977",
    "youtube_theme_url": "https://www.youtube.com/watch?v=1ddPOiRH1v4"
}