{
    "adult": false,
    "backdrop_path": "/b08BDQPq42AoLMfhi7DtTOoYqVu.jpg",
    "belongs_to_collection": null,
    "budget": 72000000,
    "genres": [
        {
            "id": 53,
            "name": "Thriller"
        },
        {
            "id": 80,
            "name": "Crime"
        },
        {
            "id": 27,
            "name": "Horror"
        },
        {
            "id": 9648,
            "name": "Mystery"
        }
    ],
    "homepage": "https://www.netflix.com/title/81444818",
    "id": 800815,
    "imdb_id": "tt14138650",
    "origin_country": [
        "US"
    ],
    "original_language": "en",
    "original_title": "The Pale Blue Eye",
    "overview": "West Point, New York, 1830. When a cadet at the burgeoning military academy is found hanged with his heart cut out, the top brass summons former New York City constable Augustus Landor to investigate. While attempting to solve this grisly mystery, the reluctant detective engages the help of one of the cadets: a strange but brilliant young fellow by the name of Edgar Allan Poe.",
    "popularity": 5.8052,
    "poster_path": "/9xkGlFRqrN8btTLU0KQvOfn2PHr.jpg",
    "production_companies": [
        {
            "id": 10246,
            "logo_path": "/rREvQNWAxkDfY9CDn2c5YxEMPdP.png",
            "name": "Cross Creek Pictures",
            "origin_country": "US"
        },
        {
            "id": 47169,
            "logo_path": null,
            "name": "Le Grisbi Productions",
            "origin_country": "US"
        }
    ],
    "production_countries": [
        {
            "iso_3166_1": "US",
            "name": "United States of America"
        }
    ],
    "release_date": "2022-12-22",
    "revenue": 0,
    "runtime": 128,
    "spoken_languages": [
        {
            "english_name": "English",
            "iso_639_1": "en",
            "name": "English"
        },
        {
            "english_name": "French",
            "iso_639_1": "fr",
            "name": "Fran\u00e7ais"
        },
        {
            "english_name": "Latin",
            "iso_639_1": "la",
            "name": "Latin"
        }
    ],
    "status": "Released",
    "tagline": "Every heart tells a tale.",
    "title": "The Pale Blue Eye",
    "video": false,
    "vote_average": 6.814,
    "vote_count": 2051,
    "youtube_theme_added": 1721853917,
    "youtube_theme_added_by": "118304977",
    "youtube_theme_edited": 1721853917,
    "youtube_theme_edited_by": "118304977",
    "youtube_theme_url": "https://www.youtube.com/watch?v=j5b57Nh_RpM"
}