{
    "adult": false,
    "backdrop_path": "/u7pSF7fAo2mCBOz1d5QPIK9yf2v.jpg",
    "belongs_to_collection": null,
    "budget": 0,
    "genres": [
        {
            "id": 28,
            "name": "Action"
        },
        {
            "id": 35,
            "name": "Comedy"
        }
    ],
    "homepage": "",
    "id": 8833,
    "imdb_id": "tt0087481",
    "original_language": "it",
    "original_title": "Non c'\u00e8 due senza quattro",
    "overview": "A stuntman and a saxophonist stand in for two billionaires threatened by killers.",
    "popularity": 15.002,
    "poster_path": "/lenzKtDEaH3SsI4eZJwvbUAL4IJ.jpg",
    "production_companies": [
        {
            "id": 2549,
            "logo_path": null,
            "name": "Trans-Cinema TV",
            "origin_country": "US"
        }
    ],
    "production_countries": [
        {
            "iso_3166_1": "IT",
            "name": "Italy"
        }
    ],
    "release_date": "1984-10-19",
    "revenue": 0,
    "runtime": 99,
    "spoken_languages": [
        {
            "english_name": "English",
            "iso_639_1": "en",
            "name": "English"
        },
        {
            "english_name": "Portuguese",
            "iso_639_1": "pt",
            "name": "Portugu\u00eas"
        }
    ],
    "status": "Released",
    "tagline": "",
    "title": "Double Trouble",
    "video": false,
    "vote_average": 6.932,
    "vote_count": 455,
    "youtube_theme_added": 1674249912,
    "youtube_theme_added_by": 19782651,
    "youtube_theme_edited": 1674249912,
    "youtube_theme_edited_by": 19782651,
    "youtube_theme_url": "https://www.youtube.com/watch?v=cp4VlKLD7DU"
}