{
    "adult": false,
    "backdrop_path": "/viU23X3BIycUFf6TOlm9c7TxLgM.jpg",
    "belongs_to_collection": {
        "backdrop_path": "/aabPyPAA6E8hJ7tUipwunr3Itzb.jpg",
        "id": 86024,
        "name": "Legally Blonde Collection",
        "poster_path": "/y33vhP9H5wJCnWMZnLBpSNSs7oA.jpg"
    },
    "budget": 18000000,
    "genres": [
        {
            "id": 35,
            "name": "Comedy"
        },
        {
            "id": 10749,
            "name": "Romance"
        }
    ],
    "homepage": "",
    "id": 8835,
    "imdb_id": "tt0250494",
    "origin_country": [
        "US"
    ],
    "original_language": "en",
    "original_title": "Legally Blonde",
    "overview": "Fashionable sorority queen Elle Woods has it all, but, she wants nothing more than to be Mrs. Warner Huntington III. But he dumps her before heading to Harvard Law School. Elle rallies all of her resources and gets into Harvard, determined to win him back. While there, she figures out that there is more to herself than just good looks.",
    "popularity": 7.4396,
    "poster_path": "/9ohlMrJHQqKhfUKh7Zr3JQqHNLZ.jpg",
    "production_companies": [
        {
            "id": 21,
            "logo_path": "/usUnaYV6hQnlVAXP6r4HwrlLFPG.png",
            "name": "Metro-Goldwyn-Mayer",
            "origin_country": "US"
        },
        {
            "id": 2527,
            "logo_path": "/mNSqvPrlkAcdQlEZ3Ttmx75Z8Xw.png",
            "name": "Marc Platt Productions",
            "origin_country": "US"
        }
    ],
    "production_countries": [
        {
            "iso_3166_1": "US",
            "name": "United States of America"
        }
    ],
    "release_date": "2001-07-13",
    "revenue": 141778365,
    "runtime": 96,
    "spoken_languages": [
        {
            "english_name": "English",
            "iso_639_1": "en",
            "name": "English"
        }
    ],
    "status": "Released",
    "tagline": "Boldly going where no blonde has gone.",
    "title": "Legally Blonde",
    "video": false,
    "vote_average": 6.813,
    "vote_count": 4390,
    "youtube_theme_added": 1720404658,
    "youtube_theme_added_by": "118304977",
    "youtube_theme_edited": 1720404658,
    "youtube_theme_edited_by": "118304977",
    "youtube_theme_url": "https://www.youtube.com/watch?v=Q0_p751ewFY"
}