{
    "adult": false,
    "backdrop_path": "/kIQszOniJOd1ULFUfdk4yDR0W5c.jpg",
    "belongs_to_collection": null,
    "budget": 5952000,
    "genres": [
        {
            "id": 27,
            "name": "Horror"
        },
        {
            "id": 878,
            "name": "Science Fiction"
        },
        {
            "id": 9648,
            "name": "Mystery"
        }
    ],
    "homepage": "",
    "id": 837,
    "imdb_id": "tt0086541",
    "original_language": "en",
    "original_title": "Videodrome",
    "overview": "As the president of a trashy TV channel, Max Renn is desperate for new programming to attract viewers. When he happens upon \"Videodrome,\" a TV show dedicated to gratuitous torture and punishment, Max sees a potential hit and broadcasts the show on his channel. However, after his girlfriend auditions for the show and never returns, Max investigates the truth behind Videodrome and discovers that the graphic violence may not be as fake as he thought.",
    "popularity": 23.128,
    "poster_path": "/qqqkiZSU9EBGZ1KiDmfn07S7qvv.jpg",
    "production_companies": [
        {
            "id": 542,
            "logo_path": null,
            "name": "Guardian Trust Company",
            "origin_country": "CA"
        },
        {
            "id": 6160,
            "logo_path": null,
            "name": "Filmplan International",
            "origin_country": "CA"
        },
        {
            "id": 541,
            "logo_path": null,
            "name": "Famous Players",
            "origin_country": "CA"
        },
        {
            "id": 4952,
            "logo_path": null,
            "name": "Canadian Film Development Corporation",
            "origin_country": "CA"
        }
    ],
    "production_countries": [
        {
            "iso_3166_1": "CA",
            "name": "Canada"
        }
    ],
    "release_date": "1983-02-04",
    "revenue": 2120439,
    "runtime": 88,
    "spoken_languages": [
        {
            "english_name": "English",
            "iso_639_1": "en",
            "name": "English"
        },
        {
            "english_name": "Japanese",
            "iso_639_1": "ja",
            "name": "\u65e5\u672c\u8a9e"
        }
    ],
    "status": "Released",
    "tagline": "First it controls your mind. Then it destroys your body.",
    "title": "Videodrome",
    "video": false,
    "vote_average": 7.294,
    "vote_count": 1989,
    "youtube_theme_added": 1674874283,
    "youtube_theme_added_by": "15357950",
    "youtube_theme_edited": 1674874283,
    "youtube_theme_edited_by": "15357950",
    "youtube_theme_url": "https://www.youtube.com/watch?v=Nz9t2X-jaxI"
}