{
    "adult": false,
    "backdrop_path": "/x085XrfEmU31QeXgMFttmuoGr0Y.jpg",
    "belongs_to_collection": {
        "backdrop_path": "/liImaqVpPGo3ddLWkJPeJxvaqCI.jpg",
        "id": 1565,
        "name": "28 Days/Weeks/Years Later Collection",
        "poster_path": "/2DMKMinwjGb45rC2nA4nr1JsT37.jpg"
    },
    "budget": 8000000,
    "genres": [
        {
            "id": 27,
            "name": "Horror"
        },
        {
            "id": 53,
            "name": "Thriller"
        },
        {
            "id": 878,
            "name": "Science Fiction"
        }
    ],
    "homepage": "https://www.sonypictures.com/movies/28dayslater",
    "id": 170,
    "imdb_id": "tt0289043",
    "origin_country": [
        "GB"
    ],
    "original_language": "en",
    "original_title": "28 Days Later",
    "overview": "Twenty-eight days after a killer virus was accidentally unleashed from a British research facility, a small group of London survivors are caught in a desperate struggle to protect themselves from the infected. Carried by animals and humans, the virus turns those it infects into homicidal maniacs -- and it's absolutely impossible to contain.",
    "popularity": 15.4707,
    "poster_path": "/sQckQRt17VaWbo39GIu0TMOiszq.jpg",
    "production_companies": [
        {
            "id": 284,
            "logo_path": "/6a26if3IKy7mlrQuGHHVp6ufQtF.png",
            "name": "DNA Films",
            "origin_country": "GB"
        }
    ],
    "production_countries": [
        {
            "iso_3166_1": "GB",
            "name": "United Kingdom"
        }
    ],
    "release_date": "2002-10-31",
    "revenue": 85032676,
    "runtime": 113,
    "spoken_languages": [
        {
            "english_name": "Spanish",
            "iso_639_1": "es",
            "name": "Espa\u00f1ol"
        },
        {
            "english_name": "English",
            "iso_639_1": "en",
            "name": "English"
        }
    ],
    "status": "Released",
    "tagline": "The days are numbered.",
    "title": "28 Days Later",
    "video": false,
    "vote_average": 7.236,
    "vote_count": 8043,
    "youtube_theme_added": 1689273520,
    "youtube_theme_added_by": "88998541",
    "youtube_theme_edited": 1689273520,
    "youtube_theme_edited_by": "88998541",
    "youtube_theme_url": "https://www.youtube.com/watch?v=DbwlGv9SWfY"
}