{
    "adult": false,
    "backdrop_path": "/29BCwmpV9HQUekAGlJLplkslRRf.jpg",
    "belongs_to_collection": {
        "backdrop_path": "/8oss4BUsACgNItOaI1dPoCWCK1T.jpg",
        "id": 64748,
        "name": "Silent Hill Collection",
        "poster_path": "/4cJgWqtVfVxxzpqyKkUtClHY0VM.jpg"
    },
    "budget": 50000000,
    "genres": [
        {
            "id": 27,
            "name": "Horror"
        },
        {
            "id": 9648,
            "name": "Mystery"
        }
    ],
    "homepage": "https://www.sonypictures.com/movies/silenthill",
    "id": 588,
    "imdb_id": "tt0384537",
    "origin_country": [
        "CA",
        "FR"
    ],
    "original_language": "en",
    "original_title": "Silent Hill",
    "overview": "Rose, a desperate mother takes her adopted daughter, Sharon, to the town of Silent Hill in an attempt to cure her of her ailment. After a violent car crash, Sharon disappears and Rose begins a desperate search to get her back. She descends into the center of the twisted reality of a town's terrible secret. Pursued by grotesquely deformed creatures and townspeople stuck in permanent purgatory, Rose begins to uncover the truth behind the apocalyptic disaster that burned the town 30 years earlier.",
    "popularity": 47.062,
    "poster_path": "/r0bEDWO2w4a43K2xTNSF284qOsc.jpg",
    "production_companies": [
        {
            "id": 341,
            "logo_path": null,
            "name": "Silent Hill DCP Inc.",
            "origin_country": "CA"
        },
        {
            "id": 342,
            "logo_path": "/kZ99mxyNvNgyAFjm7rcl9vfYmU8.png",
            "name": "Davis Films",
            "origin_country": "FR"
        },
        {
            "id": 55914,
            "logo_path": "/fLZm5yRhOmaYb82wvCMOPiClMMB.png",
            "name": "Konami",
            "origin_country": "JP"
        },
        {
            "id": 16419,
            "logo_path": "/8ppVamMu9jnA72kOi4e9grvx6Ex.png",
            "name": "Metropolitan Filmexport",
            "origin_country": "FR"
        },
        {
            "id": 803,
            "logo_path": "/jEMVaCuEjQ3lzkhakWDKNVjwd9Q.png",
            "name": "Alliance Atlantis",
            "origin_country": "CA"
        }
    ],
    "production_countries": [
        {
            "iso_3166_1": "CA",
            "name": "Canada"
        },
        {
            "iso_3166_1": "FR",
            "name": "France"
        },
        {
            "iso_3166_1": "JP",
            "name": "Japan"
        }
    ],
    "release_date": "2006-04-21",
    "revenue": 100600000,
    "runtime": 125,
    "spoken_languages": [
        {
            "english_name": "English",
            "iso_639_1": "en",
            "name": "English"
        }
    ],
    "status": "Released",
    "tagline": "We've been expecting you.",
    "title": "Silent Hill",
    "video": false,
    "vote_average": 6.6,
    "vote_count": 4125,
    "youtube_theme_added": 1675703697,
    "youtube_theme_added_by": "15357950",
    "youtube_theme_edited": 1675703697,
    "youtube_theme_edited_by": "15357950",
    "youtube_theme_url": "https://www.youtube.com/watch?v=RVsZvxY-coc"
}