{
    "adult": false,
    "backdrop_path": "/pfmRCfljWnfUzjleFgtPDYBgrkG.jpg",
    "belongs_to_collection": null,
    "budget": 75000000,
    "genres": [
        {
            "id": 28,
            "name": "Action"
        },
        {
            "id": 53,
            "name": "Thriller"
        },
        {
            "id": 878,
            "name": "Science Fiction"
        }
    ],
    "homepage": "",
    "id": 7551,
    "imdb_id": "tt0453467",
    "original_language": "en",
    "original_title": "D\u00e9j\u00e0 Vu",
    "overview": "Called in to recover evidence in the aftermath of a horrific explosion on a New Orleans ferry, Federal agent Doug Carlin gets pulled away from the scene and taken to a top-secret government lab that uses a time-shifting surveillance device to help prevent crime.",
    "popularity": 30.578,
    "poster_path": "/wJAz3m9kTbdTWfQ2ZJEFojWKeoj.jpg",
    "production_companies": [
        {
            "id": 9195,
            "logo_path": "/ou5BUbtulr6tIt699q6xJiEQTR9.png",
            "name": "Touchstone Pictures",
            "origin_country": "US"
        },
        {
            "id": 130,
            "logo_path": "/c9dVHPOL3cqCr2593Ahk0nEKTEM.png",
            "name": "Jerry Bruckheimer Films",
            "origin_country": "US"
        },
        {
            "id": 1645,
            "logo_path": "/6Ry6uNBaa0IbbSs1XYIgX5DkA9r.png",
            "name": "Scott Free Productions",
            "origin_country": "GB"
        }
    ],
    "production_countries": [
        {
            "iso_3166_1": "GB",
            "name": "United Kingdom"
        },
        {
            "iso_3166_1": "US",
            "name": "United States of America"
        }
    ],
    "release_date": "2006-11-22",
    "revenue": 180557550,
    "runtime": 126,
    "spoken_languages": [
        {
            "english_name": "English",
            "iso_639_1": "en",
            "name": "English"
        }
    ],
    "status": "Released",
    "tagline": "If you think it's just a feeling, go back... and look again.",
    "title": "D\u00e9j\u00e0 Vu",
    "video": false,
    "vote_average": 6.853,
    "vote_count": 4430,
    "youtube_theme_added": 1699801400,
    "youtube_theme_added_by": "118304977",
    "youtube_theme_edited": 1699801400,
    "youtube_theme_edited_by": "118304977",
    "youtube_theme_url": "https://www.youtube.com/watch?v=jnF_S4sOw-M"
}