{
    "adult": false,
    "backdrop_path": "/xMjAkXpCb55FTAV7By31p3TQMxb.jpg",
    "belongs_to_collection": null,
    "budget": 20000000,
    "genres": [
        {
            "id": 27,
            "name": "Horror"
        }
    ],
    "homepage": "http://www.deadsilencemovie.net/",
    "id": 14001,
    "imdb_id": "tt0455760",
    "origin_country": [
        "US"
    ],
    "original_language": "en",
    "original_title": "Dead Silence",
    "overview": "Jamie returns to his hometown in search of answers to his wife's murder, which occurred after receiving a weird package containing a ventriloquist dummy named Billy, which may be linked to the legend of ventriloquist Mary Shaw. Destined to find out the truth, Jamie goes to the town of Raven's Fair, where Shaw used to perform and is buried. But Jamie is in for more than he expected.",
    "popularity": 74.38,
    "poster_path": "/9CR1G9kVycsbYfnDO40JClrYEWr.jpg",
    "production_companies": [
        {
            "id": 23019,
            "logo_path": null,
            "name": "Evolution Entertainment",
            "origin_country": ""
        },
        {
            "id": 33,
            "logo_path": "/8lvHyhjr8oUKOOy2dKXoALWKdp0.png",
            "name": "Universal Pictures",
            "origin_country": "US"
        },
        {
            "id": 2061,
            "logo_path": "/o9LbN33hRaj4qcebUv1bikyXeoB.png",
            "name": "Twisted Pictures",
            "origin_country": "US"
        }
    ],
    "production_countries": [
        {
            "iso_3166_1": "US",
            "name": "United States of America"
        }
    ],
    "release_date": "2007-03-16",
    "revenue": 22217407,
    "runtime": 89,
    "spoken_languages": [
        {
            "english_name": "English",
            "iso_639_1": "en",
            "name": "English"
        }
    ],
    "status": "Released",
    "tagline": "You scream. You die.",
    "title": "Dead Silence",
    "video": false,
    "vote_average": 6.423,
    "vote_count": 2142,
    "youtube_theme_added": 1694723454,
    "youtube_theme_added_by": "118304977",
    "youtube_theme_edited": 1694723454,
    "youtube_theme_edited_by": "118304977",
    "youtube_theme_url": "https://www.youtube.com/watch?v=UI2WuKFX7u0"
}