{
    "adult": false,
    "backdrop_path": "/R0p2aJVD7NTrCJFbDlTPKoVCCz.jpg",
    "belongs_to_collection": null,
    "budget": 0,
    "genres": [
        {
            "id": 35,
            "name": "Comedy"
        },
        {
            "id": 28,
            "name": "Action"
        },
        {
            "id": 18,
            "name": "Drama"
        }
    ],
    "homepage": "",
    "id": 10074,
    "imdb_id": "tt0787475",
    "original_language": "en",
    "original_title": "Hot Rod",
    "overview": "For Rod Kimble, performing stunts is a way of life, even though he is rather accident-prone. Poor Rod cannot even get any respect from his stepfather, Frank, who beats him up in weekly sparring matches. When Frank falls ill, Rod devises his most outrageous stunt yet to raise money for Frank's operation -- and then Rod will kick Frank's butt.",
    "popularity": 12.524,
    "poster_path": "/jRkt03dXCVKnbvcQm3ygU1cjg9Y.jpg",
    "production_companies": [
        {
            "id": 4,
            "logo_path": "/gz66EfNoYPqHTYI4q9UEN4CbHRc.png",
            "name": "Paramount",
            "origin_country": "US"
        },
        {
            "id": 1756,
            "logo_path": "/d7YyNzysIF0lSb4lJRf1ar6MHxi.png",
            "name": "Broadway Video",
            "origin_country": "US"
        },
        {
            "id": 58553,
            "logo_path": null,
            "name": "Michaels-Goldwyn",
            "origin_country": "US"
        },
        {
            "id": 53808,
            "logo_path": null,
            "name": "The Lonely Island",
            "origin_country": "US"
        }
    ],
    "production_countries": [
        {
            "iso_3166_1": "US",
            "name": "United States of America"
        }
    ],
    "release_date": "2007-08-03",
    "revenue": 14353654,
    "runtime": 88,
    "spoken_languages": [
        {
            "english_name": "English",
            "iso_639_1": "en",
            "name": "English"
        }
    ],
    "status": "Released",
    "tagline": "Smack destiny in the face.",
    "title": "Hot Rod",
    "video": false,
    "vote_average": 6.369,
    "vote_count": 884,
    "youtube_theme_added": 1676129777,
    "youtube_theme_added_by": "88998541",
    "youtube_theme_edited": 1676129777,
    "youtube_theme_edited_by": "88998541",
    "youtube_theme_url": "https://www.youtube.com/watch?v=3Li9wi9lpEg"
}