{
    "adult": false,
    "backdrop_path": "/8nh70OvIsJKpfZdTMZoMJMb8aVE.jpg",
    "belongs_to_collection": null,
    "budget": 12000000,
    "genres": [
        {
            "id": 18,
            "name": "Drama"
        }
    ],
    "homepage": "",
    "id": 392982,
    "imdb_id": "tt5301662",
    "origin_country": [
        "US"
    ],
    "original_language": "en",
    "original_title": "Marshall",
    "overview": "Thurgood Marshall, the first African-American Supreme Court Justice, battles through one of his career-defining cases.",
    "popularity": 1.3287,
    "poster_path": "/2KfdXsXTCbMie0wB1mSmIX60C2F.jpg",
    "production_companies": [
        {
            "id": 82061,
            "logo_path": null,
            "name": "Chestnut Ridge",
            "origin_country": "US"
        },
        {
            "id": 128493,
            "logo_path": null,
            "name": "Starlight Culture Entertainment Group",
            "origin_country": "HK"
        },
        {
            "id": 152974,
            "logo_path": null,
            "name": "Hudlin Entertainment",
            "origin_country": "US"
        },
        {
            "id": 11341,
            "logo_path": "/xytTBODEy3p20ksHL4Ftxr483Iv.png",
            "name": "Stage 6 Films",
            "origin_country": "US"
        },
        {
            "id": 10427,
            "logo_path": "/3u5sNgPRbba0ND3SUMXPTT7On9h.png",
            "name": "Open Road Films",
            "origin_country": "US"
        }
    ],
    "production_countries": [
        {
            "iso_3166_1": "HK",
            "name": "Hong Kong"
        },
        {
            "iso_3166_1": "US",
            "name": "United States of America"
        }
    ],
    "release_date": "2017-10-13",
    "revenue": 10051659,
    "runtime": 118,
    "spoken_languages": [
        {
            "english_name": "English",
            "iso_639_1": "en",
            "name": "English"
        }
    ],
    "status": "Released",
    "tagline": "Justice has a name.",
    "title": "Marshall",
    "video": false,
    "vote_average": 7.245,
    "vote_count": 654,
    "youtube_theme_added": 1720640335,
    "youtube_theme_added_by": "118304977",
    "youtube_theme_edited": 1720640335,
    "youtube_theme_edited_by": "118304977",
    "youtube_theme_url": "https://www.youtube.com/watch?v=RwZU7BbP_wY"
}