{
    "adult": false,
    "backdrop_path": "/bGRKHQsmLUz2hQB8W3nYnCIc9Y0.jpg",
    "created_by": [],
    "episode_run_time": [
        24
    ],
    "first_air_date": "2023-01-08",
    "genres": [
        {
            "id": 16,
            "name": "Animation"
        },
        {
            "id": 10759,
            "name": "Action & Adventure"
        },
        {
            "id": 10765,
            "name": "Sci-Fi & Fantasy"
        }
    ],
    "homepage": "https://nierautomata-anime.com",
    "id": 158373,
    "in_production": false,
    "languages": [
        "ja"
    ],
    "last_air_date": "2024-09-27",
    "last_episode_to_air": {
        "air_date": "2024-09-27",
        "episode_number": 24,
        "episode_type": "finale",
        "id": 5458243,
        "name": "the [E]nd of YoRHa",
        "overview": "Everything that lives is designed to end.\n\n\uff1cThey\uff1e are perpetually trapped\u2026in a never-ending spiral of life and death.",
        "production_code": "",
        "runtime": 24,
        "season_number": 1,
        "show_id": 158373,
        "still_path": "/gD19N5wfjzcwMH096N9wE6q6dUD.jpg",
        "vote_average": 7.5,
        "vote_count": 2
    },
    "name": "NieR:Automata Ver1.1a",
    "networks": [
        {
            "id": 343,
            "logo_path": "/9rNqtDYAnD6yTOutvHI3synSEs2.png",
            "name": "Gunma TV",
            "origin_country": "JP"
        },
        {
            "id": 614,
            "logo_path": "/hSdroyVthq3CynxTIIY7lnS8w1.png",
            "name": "Tokyo MX",
            "origin_country": "JP"
        },
        {
            "id": 861,
            "logo_path": "/JQ5bx6n7Qmdmyqz6sqjo5Fz2iR.png",
            "name": "BS11",
            "origin_country": "JP"
        },
        {
            "id": 2478,
            "logo_path": "/2v82HpzoKRveJEJcGHkeTcktMRM.png",
            "name": "Tochigi TV",
            "origin_country": "JP"
        }
    ],
    "next_episode_to_air": null,
    "number_of_episodes": 24,
    "number_of_seasons": 1,
    "origin_country": [
        "JP"
    ],
    "original_language": "ja",
    "original_name": "NieR:Automata Ver1.1a",
    "overview": "The distant future, 5012.\n\nThe sudden aerial invasion of Earth by \uff1cAliens\uff1e and their creations \uff1cMachine Lifeforms\uff1e led mankind to the brink of extinction. The surviving number of humans who took refuge on the moon to organize a counterattack using \uff1candroid\uff1e soldiers to recapture Earth.\n\nHowever, the war reaches a stalemate as the \uff1cMachine Lifeforms\uff1e continue to multiply infinitely. In turn, humanity deploys anew unit of android soldiers as an ultimate weapon: \uff1cYoRHa\uff1e\n\nNewly dispatched to Earth \uff1c2B\uff1e joins \uff1c9S\uff1e, the analyst currently stationed there, where amid their mission, they encounter a myriad of mysterious phenomena...\n\nThis is the story of these lifeless \uff1candroids\uff1e and their endless fight for the sake of mankind.",
    "popularity": 14.4805,
    "poster_path": "/qHSCYOXHV3EKXKkMxUvC9rGx4Av.jpg",
    "production_companies": [
        {
            "id": 10038,
            "logo_path": "/nCueXKwYIEXrZ5ofqSJBO1YcmRr.png",
            "name": "Square Enix",
            "origin_country": "JP"
        },
        {
            "id": 2883,
            "logo_path": "/rDYExnBV61jGQnkhVVrPN4Yl7O1.png",
            "name": "Aniplex",
            "origin_country": "JP"
        },
        {
            "id": 13113,
            "logo_path": "/xV5tPYKZhP2Ko9dOh5A3FahuKsx.png",
            "name": "A-1 Pictures",
            "origin_country": "JP"
        }
    ],
    "production_countries": [
        {
            "iso_3166_1": "JP",
            "name": "Japan"
        }
    ],
    "seasons": [
        {
            "air_date": "2022-12-28",
            "episode_count": 11,
            "id": 322188,
            "name": "Specials",
            "overview": "",
            "poster_path": "/9dsHUwk2k5HvjLxyzfyedDaBaTL.jpg",
            "season_number": 0,
            "vote_average": 0.0
        },
        {
            "air_date": "2023-01-08",
            "episode_count": 24,
            "id": 245305,
            "name": "Season 1",
            "overview": "",
            "poster_path": "/kdZjekffiDLPNR5T24GAuHE3k8F.jpg",
            "season_number": 1,
            "vote_average": 7.7
        }
    ],
    "spoken_languages": [
        {
            "english_name": "Japanese",
            "iso_639_1": "ja",
            "name": "\u65e5\u672c\u8a9e"
        }
    ],
    "status": "Ended",
    "tagline": "",
    "type": "Scripted",
    "vote_average": 8.066,
    "vote_count": 174,
    "youtube_theme_added": 1715455422,
    "youtube_theme_added_by": "138393558",
    "youtube_theme_edited": 1715455422,
    "youtube_theme_edited_by": "138393558",
    "youtube_theme_url": "https://www.youtube.com/watch?v=_COPvSeS6zw"
}