[{"id": 5708, "imdb_id": "tt0421082", "title": "Control"}, {"id": 986088, "imdb_id": "tt14036276", "title": "Control"}, {"id": 9584, "imdb_id": "tt0077369", "title": "Convoy"}, {"id": 864, "imdb_id": "tt0106611", "title": "Cool Runnings"}, {"id": 3933, "imdb_id": "tt0121164", "title": "Corpse Bride"}, {"id": 888321, "imdb_id": "tt11992694", "title": "Corsage"}, {"id": 10684, "imdb_id": "tt0115956", "title": "Courage Under Fire"}, {"id": 11299, "imdb_id": "tt0275277", "title": "Cowboy Bebop: The Movie"}, {"id": 49849, "imdb_id": "tt0409847", "title": "Cowboys & Aliens"}, {"id": 1640, "imdb_id": "tt0375679", "title": "Crash"}]