[{"id": 71157, "imdb_id": "tt1661420", "title": "Polisse"}, {"id": 15283, "imdb_id": "tt0110008", "title": "Pom Poko"}, {"id": 12429, "imdb_id": "tt0876563", "title": "Ponyo"}, {"id": 11335, "imdb_id": "tt0081353", "title": "Popeye"}, {"id": 341012, "imdb_id": "tt3960412", "title": "Popstar: Never Stop Never Stopping"}, {"id": 1115239, "imdb_id": "tt27542289", "title": "Por Thozhil"}, {"id": 11621, "imdb_id": "tt0104652", "title": "Porco Rosso"}, {"id": 21484, "imdb_id": "tt0082933", "title": "Possession"}, {"id": 435615, "imdb_id": "tt5918982", "title": "Possessor"}, {"id": 106, "imdb_id": "tt0093773", "title": "Predator"}]