[{"id": 54138, "imdb_id": "tt1408101", "title": "Star Trek Into Darkness"}, {"id": 172, "imdb_id": "tt0098382", "title": "Star Trek V: The Final Frontier"}, {"id": 174, "imdb_id": "tt0102975", "title": "Star Trek VI: The Undiscovered Country"}, {"id": 199, "imdb_id": "tt0117731", "title": "Star Trek: First Contact"}, {"id": 193, "imdb_id": "tt0111280", "title": "Star Trek: Generations"}, {"id": 152, "imdb_id": "tt0079945", "title": "Star Trek: The Motion Picture"}, {"id": 11, "imdb_id": "tt0076759", "title": "Star Wars"}, {"id": 1893, "imdb_id": "tt0120915", "title": "Star Wars: Episode I - The Phantom Menace"}, {"id": 1894, "imdb_id": "tt0121765", "title": "Star Wars: Episode II - Attack of the Clones"}, {"id": 1895, "imdb_id": "tt0121766", "title": "Star Wars: Episode III - Revenge of the Sith"}]