[{"id": 36669, "title": "Die Another Day"}, {"id": 284052, "title": "Doctor Strange"}, {"id": 453395, "title": "Doctor Strange in the Multiverse of Madness"}, {"id": 8833, "title": "Double Trouble"}, {"id": 10837, "title": "DuckTales: The Movie - Treasure of the Lost Lamp"}, {"id": 614934, "title": "Elvis"}, {"id": 568124, "title": "Encanto"}, {"id": 1027014, "title": "Entergalactic"}, {"id": 259316, "title": "Fantastic Beasts and Where to Find Them"}, {"id": 338952, "title": "Fantastic Beasts: The Crimes of Grindelwald"}]