[{"id": 10201, "imdb_id": "tt1068680", "title": "Yes Man"}, {"id": 527660, "imdb_id": "tt8949056", "title": "Yes, God, Yes"}, {"id": 515195, "imdb_id": "tt8079248", "title": "Yesterday"}, {"id": 25538, "imdb_id": "tt0244316", "title": "Yi Yi"}, {"id": 11878, "imdb_id": "tt0055630", "title": "Yojimbo"}, {"id": 38219, "imdb_id": "tt0084935", "title": "Yor, the Hunter from the Future"}, {"id": 999644, "imdb_id": "tt21276878", "title": "You Are So Not Invited to My Bat Mitzvah"}, {"id": 667, "imdb_id": "tt0062512", "title": "You Only Live Twice"}, {"id": 83899, "imdb_id": "tt1853739", "title": "You're Next"}, {"id": 9489, "imdb_id": "tt0128853", "title": "You've Got Mail"}]